bpl_client/Client.py
bpl_client/__init__.py
bpl_client/__main__.py
bpl_client/commands.json
bpl_client/commands/Command.py
bpl_client/commands/__init__.py
bpl_client/commands/account/Create.py
bpl_client/commands/account/Delegate.py
bpl_client/commands/account/Send.py
bpl_client/commands/account/Status.py
bpl_client/commands/account/Transactions.py
bpl_client/commands/account/Vote.py
bpl_client/commands/account/__init__.py
bpl_client/commands/message/Sign.py
bpl_client/commands/message/Verify.py
bpl_client/commands/message/__init__.py
bpl_client/commands/network/Peers.py
bpl_client/commands/network/Status.py
bpl_client/commands/network/__init__.py
bpl_client/commands/network/config/New.py
bpl_client/commands/network/config/Show.py
bpl_client/commands/network/config/Use.py
bpl_client/commands/network/config/__init__.py
bpl_client/helpers/Constants.py
bpl_client/helpers/Exceptions.py
bpl_client/helpers/Util.py
bpl_client/helpers/__init__.py
bpl_client/network/NetworkConfig.py
bpl_client/network/__init__.py
bpl_client/network/configs.json
bpl_client-0.1.1.dist-info/METADATA
bpl_client-0.1.1.dist-info/RECORD
bpl_client-0.1.1.dist-info/WHEEL
bpl_client-0.1.1.dist-info/entry_points.txt
bpl_client-0.1.1.dist-info/top_level.txt
