Metadata-Version: 2.1
Name: bpl-client
Version: 0.1.1
Summary: A CLI Client for the Blockpool Blockchain.
Home-page: https://github.com/DuneRoot/bpl-cli
Author: Alistair O'Brien
Author-email: alistair.o'brien@ellesmere.com
License: UNKNOWN
Platform: UNKNOWN
Requires-Dist: docopt
Requires-Dist: bpl-lib (>=0.1.0)
Requires-Dist: bpl-api (>=0.1.0)
Requires-Dist: ascii-table (>=0.1.0)
Requires-Dist: mnemonic
